theseus/__init__.py
theseus/node.py
theseus-0.0.5.dist-info/METADATA
theseus-0.0.5.dist-info/WHEEL
theseus-0.0.5.dist-info/top_level.txt
theseus-0.0.5.dist-info/RECORD
